sr3_x/__init__.py
sr3_x/models/__init__.py
sr3_x/models/unet/__init__.py
sr3_x-0.0.1.dist-info/LICENSE
sr3_x-0.0.1.dist-info/WHEEL
sr3_x-0.0.1.dist-info/METADATA
sr3_x-0.0.1.dist-info/RECORD
