Metadata-Version: 2.1
Name: sr3-x
Version: 0.0.1
Summary: An implementation of SR3 from Google
Author: paulcjh
Author-email: paulcjh@protonmail.com
Requires-Python: >=3.9,<4.0
Classifier: Programming Language :: Python :: 3
Classifier: Programming Language :: Python :: 3.10
Classifier: Programming Language :: Python :: 3.9
Requires-Dist: torch (>=1.11.0,<2.0.0)
